{
  "terms-radio-1": {
    "component": {
      "componentType": "RadioButton",
      "appearance": {
        "size": "sm",
        "description": {
          "color": "#475467",
          "variant": "text-xs",
          "weight": "regular"
        },
        "styles": {
          "padding": {
            "all": "0px"
          },
          "margin": {
            "all": "0px"
          },
          "backgroundColor": "transparent",
          "borderColor": "#2C2C2C",
          "borderWidth": {
            "all": "border-1"
          },
          "width": "344px",
          "height": "36px"
        },
        "label": {
          "color": "#344054",
          "variant": "text-sm",
          "weight": "medium"
        }
      },
      "content": {
        "label": "Remember me",
        "description": "Save my login details for next time.",
        "checked": true
      }
    },
    "visibility": {
      "value": true
    },
    "dpOn": [],
    "displayName": "RadioButton_0d5ph",
    "dataSourceIds": [],
    "id": "terms-radio-1",
    "parentId": "root_id"
  }
}